{
  "indexes": [
    {
      "collectionGroup": "matches",
      "queryScope": "COLLECTION",
      "fields": [
        { "fieldPath": "participants", "arrayConfig": "CONTAINS" },
        { "fieldPath": "hasScheduledDate", "order": "ASCENDING" },
        { "fieldPath": "__name__", "order": "ASCENDING" }
      ]
    },
    {
      "collectionGroup": "dateRequests",
      "queryScope": "COLLECTION",
      "fields": [
        { "fieldPath": "participants", "arrayConfig": "CONTAINS" },
        { "fieldPath": "status", "order": "ASCENDING" },
        { "fieldPath": "scheduledFor", "order": "ASCENDING" }
      ]
    }
  ],
  "fieldOverrides": []
} 